steam_magnetic_calculations/Magnetic_Coil.py
steam_magnetic_calculations/__init__.py
steam_magnetic_calculations/steam-magnetic-calculation.py
steam_magnetic_calculations-0.1.dist-info/METADATA
steam_magnetic_calculations-0.1.dist-info/WHEEL
steam_magnetic_calculations-0.1.dist-info/top_level.txt
steam_magnetic_calculations-0.1.dist-info/RECORD
